jackmatchmaker/__init__.py
jackmatchmaker/__main__.py
jackmatchmaker/version.py
jack_matchmaker-0.11.0.dist-info/METADATA
jack_matchmaker-0.11.0.dist-info/WHEEL
jack_matchmaker-0.11.0.dist-info/entry_points.txt
jack_matchmaker-0.11.0.dist-info/licenses/LICENSE
jack_matchmaker-0.11.0.dist-info/RECORD
