Metadata-Version: 2.1
Name: jack-matchmaker
Version: 0.11.0
Summary: Auto-connect JACK ports as they appear using patterns
Project-URL: Homepage, https://github.com/SpotlightKid/jack-matchmaker
Project-URL: Source, https://github.com/SpotlightKid/jack-matchmaker
Project-URL: Bug Tracker, https://github.com/SpotlightKid/jack-matchmaker/issues
Author-email: Christopher Arndt <info@chrisarndt.de>
License-Expression: GPL-2.0
License-File: LICENSE
Keywords: JACK,MIDI,audio,multimedia,music
Classifier: Development Status :: 4 - Beta
Classifier: Environment :: Console
Classifier: Intended Audience :: End Users/Desktop
Classifier: License :: OSI Approved :: GNU General Public License v2 (GPLv2)
Classifier: Operating System :: MacOS :: MacOS X
Classifier: Operating System :: Microsoft :: Windows
Classifier: Operating System :: POSIX :: Linux
Classifier: Programming Language :: Python
Classifier: Programming Language :: Python :: 3
Classifier: Programming Language :: Python :: 3 :: Only
Classifier: Programming Language :: Python :: 3.8
Classifier: Programming Language :: Python :: 3.9
Classifier: Programming Language :: Python :: 3.10
Classifier: Programming Language :: Python :: 3.11
Classifier: Topic :: Multimedia :: Sound/Audio
Classifier: Topic :: Multimedia :: Sound/Audio :: MIDI
Classifier: Topic :: Utilities
Requires-Python: >=3.8
Requires-Dist: cachetools
Requires-Dist: pyjacklib
